lambda_layer_version_cleaner/__init__.py
lambda_layer_version_cleaner/py.typed
lambda_layer_version_cleaner/_jsii/__init__.py
lambda_layer_version_cleaner/_jsii/lambda-layer-version-cleaner@0.0.10.jsii.tgz
lambda_layer_version_cleaner-0.0.10.dist-info/LICENSE
lambda_layer_version_cleaner-0.0.10.dist-info/METADATA
lambda_layer_version_cleaner-0.0.10.dist-info/WHEEL
lambda_layer_version_cleaner-0.0.10.dist-info/top_level.txt
lambda_layer_version_cleaner-0.0.10.dist-info/RECORD
